gtbp/__init__.py
gtbp/optimiser.py
gtbp-0.0.1a1.dist-info/WHEEL
gtbp-0.0.1a1.dist-info/METADATA
gtbp-0.0.1a1.dist-info/RECORD
