Metadata-Version: 2.3
Name: gtbp
Version: 0.0.1a1
Summary: Get The Best Parameters
Author: Gabriel Choong
Author-email: Gabriel Choong <gabrielchoonggeliang@gmail.com>
Requires-Python: >=3.10
